razer_chroma_keyboard/__init__.py
razer_chroma_keyboard/__main__.py
razer_chroma_keyboard/api.py
razer_chroma_keyboard-0.0.1.post2.dist-info/METADATA
razer_chroma_keyboard-0.0.1.post2.dist-info/WHEEL
razer_chroma_keyboard-0.0.1.post2.dist-info/licenses/LICENSE
razer_chroma_keyboard-0.0.1.post2.dist-info/RECORD
