Metadata-Version: 2.1
Name: razer_chroma_keyboard
Version: 0.0.1.post2
Summary: Razer chroma compatible keyboard backlight driving library.
Project-URL: Homepage, https://github.com/TheVroum/keyboard_light_razer_chroma_easy_manipulation_library
Project-URL: Bug Tracker, https://github.com/TheVroum/keyboard_light_razer_chroma_easy_manipulation_library/issues
Author: Jean Oustry
License-File: LICENSE
Classifier: License :: OSI Approved :: MIT License
Classifier: Operating System :: Microsoft
Classifier: Programming Language :: Python :: 3
Requires-Python: >=3.9
Requires-Dist: requests
